{
  "track": "CC",
  "experiment": 620,
  "statistic": "rank_F2([C_1|y_1|...|C_k|y_k])",
  "sampling_model": "independent fresh marginal-uniform B per sample (product distribution)",
  "standing_guards": [
    "L1 exact arithmetic",
    "L2 J-twist duality",
    "L3 query-class hygiene",
    "L4 never transform LPN"
  ],
  "q_graph_formula": "(3/4)^n",
  "tables": [
    {
      "n": 2,
      "p_eff": "175/512",
      "q_graph(n)": "9/16",
      "float_q_graph": 0.5625,
      "rows": [
        {
          "m": 2,
          "single_sample": {
            "reduction": {
              "0": "151/4096",
              "1": "1779/4096",
              "2": "1083/2048"
            },
            "lpn": {
              "0": "113569/4194304",
              "1": "1616421/4194304",
              "2": "1232157/2097152"
            },
            "sd_rank": "123165/2097152",
            "sd_rank_float": 0.05872964859008789
          },
          "k_sample": [
            {
              "k": 2,
              "sd_rank_sum": "288347616585/4398046511104",
              "sd_rank_sum_float": 0.06556265738822731,
              "upper_bound_k_times_single": "123165/1048576"
            },
            {
              "k": 3,
              "sd_rank_sum": "1654424172861506865/18446744073709551616",
              "sd_rank_sum_float": 0.08968651412144897,
              "upper_bound_k_times_single": "369495/2097152"
            }
          ]
        },
        {
          "m": 3,
          "single_sample": {
            "reduction": {
              "0": "267/32768",
              "1": "6587/32768",
              "2": "10017/16384",
              "3": "735/4096"
            },
            "lpn": {
              "0": "38272753/8589934592",
              "1": "1187507713/8589934592",
              "2": "2530737363/4294967296",
              "3": "287834925/1073741824"
            },
            "sd_rank": "95159085/1073741824",
            "sd_rank_float": 0.08862380404025316
          },
          "k_sample": [
            {
              "k": 2,
              "sd_rank_sum": "313937724662486505/2305843009213693952",
              "sd_rank_sum_float": 0.1361487852416896,
              "upper_bound_k_times_single": "95159085/536870912"
            },
            {
              "k": 3,
              "sd_rank_sum": "3363744584967703518316808745/19807040628566084398385987584",
              "sd_rank_sum_float": 0.16982570228671356,
              "upper_bound_k_times_single": "285477255/1073741824"
            }
          ]
        },
        {
          "m": 4,
          "single_sample": {
            "reduction": {
              "0": "499/262144",
              "1": "24555/262144",
              "2": "74445/131072",
              "3": "11025/32768"
            },
            "lpn": {
              "0": "12897917761/17592186044416",
              "1": "803692535145/17592186044416",
              "2": "3698786841855/8796093022208",
              "3": "1172252738475/2199023255552"
            },
            "sd_rank": "432377512875/2199023255552",
            "sd_rank_float": 0.19662252856278428
          },
          "k_sample": [
            {
              "k": 2,
              "sd_rank_sum": "2293078292498739962514375/9671406556917033397649408",
              "sd_rank_sum_float": 0.2370987383276448,
              "upper_bound_k_times_single": "432377512875/1099511627776"
            },
            {
              "k": 3,
              "sd_rank_sum": "11867281179050785921404507536843390625/42535295865117307932921825928971026432",
              "sd_rank_sum_float": 0.2789984397118771,
              "upper_bound_k_times_single": "1297132538625/2199023255552"
            }
          ]
        },
        {
          "m": 5,
          "single_sample": {
            "reduction": {
              "0": "963/2097152",
              "1": "93899/2097152",
              "2": "545445/1048576",
              "3": "113925/262144"
            },
            "lpn": {
              "0": "4346598285457/36028797018963968",
              "1": "527584735761001/36028797018963968",
              "2": "4796567845041255/18014398509481984",
              "3": "3237966249354375/4503599627370496"
            },
            "sd_rank": "1280749652567175/4503599627370496",
            "sd_rank_float": 0.2843835506121495
          },
          "k_sample": [
            {
              "k": 2,
              "sd_rank_sum": "6653728625218769554742247800625/20282409603651670423947251286016",
              "sd_rank_sum_float": 0.32805414914906483,
              "upper_bound_k_times_single": "1280749652567175/2251799813685248"
            },
            {
              "k": 3,
              "sd_rank_sum": "148981993002906167490104615540687345780913290625/365375409332725729550921208179070754913983135744",
              "sd_rank_sum_float": 0.4077504648574669,
              "upper_bound_k_times_single": "3842248957701525/4503599627370496"
            }
          ]
        },
        {
          "m": 6,
          "single_sample": {
            "reduction": {
              "0": "1891/16777216",
              "1": "366219/16777216",
              "2": "4103253/8388608",
              "3": "1025325/2097152"
            },
            "lpn": {
              "0": "1464803622199009/73786976294838206464",
              "1": "343046264144744601/73786976294838206464",
              "2": "5938986123189297927/36893488147419103232",
              "3": "7695561622586583375/9223372036854775808"
            },
            "sd_rank": "3186134583588874575/9223372036854775808",
            "sd_rank_float": 0.3454414037358256
          },
          "k_sample": [
            {
              "k": 2,
              "sd_rank_sum": "38886736466983804379314056906228950625/85070591730234615865843651857942052864",
              "sd_rank_sum_float": 0.45711139038854504,
              "upper_bound_k_times_single": "3186134583588874575/4611686018427387904"
            },
            {
              "k": 3,
              "sd_rank_sum": "364045107584175491161753186040915685914496011531408859375/784637716923335095479473677900958302012794430558004314112",
              "sd_rank_sum_float": 0.46396585294375464,
              "upper_bound_k_times_single": "1"
            }
          ]
        }
      ]
    },
    {
      "n": 3,
      "p_eff": "3367/8192",
      "q_graph(n)": "27/64",
      "float_q_graph": 0.421875,
      "rows": [
        {
          "m": 2,
          "single_sample": {
            "reduction": {
              "0": "2777/393216",
              "1": "85253/393216",
              "2": "152593/196608"
            },
            "lpn": {
              "0": "23280625/4294967296",
              "1": "839519037/4294967296",
              "2": "1716083817/2147483648"
            },
            "sd_rank": "148084027/6442450944",
            "sd_rank_float": 0.022985666214178007
          },
          "k_sample": [
            {
              "k": 2,
              "sd_rank_sum": "1502818734692809625/41505174165846491136",
              "sd_rank_sum_float": 0.036207985266796916,
              "upper_bound_k_times_single": "148084027/3221225472"
            }
          ]
        },
        {
          "m": 3,
          "single_sample": {
            "reduction": {
              "0": "13295/18874368",
              "1": "840007/18874368",
              "2": "437129/1048576",
              "3": "423031/786432"
            },
            "lpn": {
              "0": "112329015625/281474976710656",
              "1": "9003536151729/281474976710656",
              "2": "53256216350967/140737488355328",
              "3": "20730834855171/35184372088832"
            },
            "sd_rank": "5414244871945/105553116266496",
            "sd_rank_float": 0.051294031511825246
          },
          "k_sample": [
            {
              "k": 2,
              "sd_rank_sum": "644136850301106791648382545/11141460353568422474092118016",
              "sd_rank_sum_float": 0.05781440043403292,
              "upper_bound_k_times_single": "5414244871945/52776558133248"
            }
          ]
        },
        {
          "m": 4,
          "single_sample": {
            "reduction": {
              "0": "7741/100663296",
              "1": "947485/100663296",
              "2": "8989295/50331648",
              "3": "2462635/4194304",
              "4": "117845/524288"
            },
            "lpn": {
              "0": "541987500390625/18446744073709551616",
              "1": "88601584556854593/18446744073709551616",
              "2": "1174836789675164091/9223372036854775808",
              "3": "1335440027955128949/2305843009213693952",
              "4": "83193854666577291/288230376151711744"
            },
            "sd_rank": "18407880778945931/288230376151711744",
            "sd_rank_float": 0.06386516586043949
          },
          "k_sample": [
            {
              "k": 2,
              "sd_rank_sum": "34286028505417739302925852789656683/332306998946228968225951765070086144",
              "sd_rank_sum_float": 0.1031757640198412,
              "upper_bound_k_times_single": "18407880778945931/144115188075855872"
            }
          ]
        }
      ]
    }
  ]
}